{
  "sections": {
    "collection": {
      "type": "sections/collection",
      "settings": {
        "type": "number",
        "id": "collections_per_page",
        "label": "Collections per page",
        "default": 50
      }
    },
    "collection-products": {
      "type": "snippets/collection-details-view",
      "settings": {
        "type": "number",
        "id": "products_per_page",
        "label": "Products per page",
        "default": 50
      }
    }
  },
  "order": ["collection"]
}
